a2wsgi-1.10.9.dist-info/METADATA
a2wsgi-1.10.9.dist-info/WHEEL
a2wsgi-1.10.9.dist-info/entry_points.txt
a2wsgi-1.10.9.dist-info/licenses/LICENSE
a2wsgi/__init__.py
a2wsgi/asgi.py
a2wsgi/asgi_typing.py
a2wsgi/py.typed
a2wsgi/wsgi.py
a2wsgi/wsgi_typing.py
a2wsgi-1.10.9.dist-info/RECORD
