Metadata-Version: 2.1
Name: a2wsgi
Version: 1.10.9
Summary: Convert WSGI app to ASGI app or ASGI app to WSGI app.
Author-Email: abersheeran <me@abersheeran.com>
License: Apache-2.0
Classifier: Programming Language :: Python :: 3
Project-URL: homepage, https://github.com/abersheeran/a2wsgi
Project-URL: repository, https://github.com/abersheeran/a2wsgi
Requires-Python: >=3.8.0
Requires-Dist: typing_extensions; python_version < "3.11"
